setup.py
src/chemeye/SimMat.py
src/chemeye/TSNE.py
src/chemeye/UMAP.py
src/chemeye/__asset_loader.py
src/chemeye/__init__.py
src/chemeye.egg-info/PKG-INFO
src/chemeye.egg-info/SOURCES.txt
src/chemeye.egg-info/dependency_links.txt
src/chemeye.egg-info/requires.txt
src/chemeye.egg-info/top_level.txt
src/chemeye/assets/__init__.py
src/test/__init__.py
src/test/test_arrays.py
src/test/test_simmat.py
src/test/test_tsne.py
src/test/test_umap.py