Metadata-Version: 1.2
Name: chemeye
Version: 0.0.6
Summary: Visualization toolset for small molecule drug discovery
Home-page: https://github.com/jwgerlach00/chemeye
Author: Jacob Gerlach
Author-email: jwgerlach00@gmail.com
License: MIT
Platform: UNKNOWN
Requires-Python: >=3.6
